trdg/__init__.py
trdg/background_generator.py
trdg/computer_text_generator.py
trdg/data_generator.py
trdg/distorsion_generator.py
trdg/handwritten_text_generator.py
trdg/run.py
trdg/string_generator.py
trdg/utils.py
trdg/dicts/ar.txt
trdg/dicts/cn.txt
trdg/dicts/de.txt
trdg/dicts/en.txt
trdg/dicts/es.txt
trdg/dicts/fr.txt
trdg/dicts/hi.txt
trdg/fonts/cn/SourceHanSans-Normal.ttf
trdg/fonts/latin/AllerDisplay.ttf
trdg/fonts/latin/Aller_Bd.ttf
trdg/fonts/latin/Aller_BdIt.ttf
trdg/fonts/latin/Aller_It.ttf
trdg/fonts/latin/Aller_Lt.ttf
trdg/fonts/latin/Aller_LtIt.ttf
trdg/fonts/latin/Aller_Rg.ttf
trdg/fonts/latin/Amatic-Bold.ttf
trdg/fonts/latin/AmaticSC-Regular.ttf
trdg/fonts/latin/BEBAS___.ttf
trdg/fonts/latin/Capture_it.ttf
trdg/fonts/latin/Capture_it_2.ttf
trdg/fonts/latin/CaviarDreams.ttf
trdg/fonts/latin/CaviarDreams_BoldItalic.ttf
trdg/fonts/latin/CaviarDreams_Italic.ttf
trdg/fonts/latin/Caviar_Dreams_Bold.ttf
trdg/fonts/latin/DroidSans-Bold.ttf
trdg/fonts/latin/DroidSans.ttf
trdg/fonts/latin/FFF_Tusj.ttf
trdg/fonts/latin/Lato-Black.ttf
trdg/fonts/latin/Lato-BlackItalic.ttf
trdg/fonts/latin/Lato-Bold.ttf
trdg/fonts/latin/Lato-BoldItalic.ttf
trdg/fonts/latin/Lato-Hairline.ttf
trdg/fonts/latin/Lato-HairlineItalic.ttf
trdg/fonts/latin/Lato-Heavy.ttf
trdg/fonts/latin/Lato-HeavyItalic.ttf
trdg/fonts/latin/Lato-Italic.ttf
trdg/fonts/latin/Lato-Light.ttf
trdg/fonts/latin/Lato-LightItalic.ttf
trdg/fonts/latin/Lato-Medium.ttf
trdg/fonts/latin/Lato-MediumItalic.ttf
trdg/fonts/latin/Lato-Regular.ttf
trdg/fonts/latin/Lato-Semibold.ttf
trdg/fonts/latin/Lato-SemiboldItalic.ttf
trdg/fonts/latin/Lato-Thin.ttf
trdg/fonts/latin/Lato-ThinItalic.ttf
trdg/fonts/latin/OpenSans-Bold.ttf
trdg/fonts/latin/OpenSans-BoldItalic.ttf
trdg/fonts/latin/OpenSans-ExtraBold.ttf
trdg/fonts/latin/OpenSans-ExtraBoldItalic.ttf
trdg/fonts/latin/OpenSans-Italic.ttf
trdg/fonts/latin/OpenSans-Light.ttf
trdg/fonts/latin/OpenSans-LightItalic.ttf
trdg/fonts/latin/OpenSans-Regular.ttf
trdg-1.6.0.dist-info/LICENSE
trdg-1.6.0.dist-info/METADATA
trdg-1.6.0.dist-info/WHEEL
trdg-1.6.0.dist-info/entry_points.txt
trdg-1.6.0.dist-info/top_level.txt
trdg-1.6.0.dist-info/RECORD
