Metadata-Version: 2.1
Name: trdg
Version: 1.6.0
Summary: TextRecognitionDataGenerator: A synthetic data generator for text recognition
Home-page: https://github.com/Belval/TextRecognitionDataGenerator
Author: Edouard Belval
Author-email: edouard@belval.org
License: MIT
Keywords: synthetic data text-recognition training-set-generator ocr dataset fake text
Platform: UNKNOWN
Classifier: Development Status :: 4 - Beta
Classifier: Intended Audience :: Developers
Classifier: License :: OSI Approved :: MIT License
Classifier: Programming Language :: Python :: 3
Classifier: Programming Language :: Python :: 3.4
Classifier: Programming Language :: Python :: 3.5
Classifier: Programming Language :: Python :: 3.6
Classifier: Programming Language :: Python :: 3.7
Requires-Dist: pillow (==7.0.0)
Requires-Dist: numpy (>=1.17.3)
Requires-Dist: requests (>=2.20.0)
Requires-Dist: opencv-python (>=4.2.0.32)
Requires-Dist: tqdm (>=4.23.0)
Requires-Dist: beautifulsoup4 (>=4.6.0)
Requires-Dist: diffimg (==0.2.3)
